nanugo/__init__.py
nanugo/cli.py
nanugo/log.py
nanugo/nanugo.py
nanugo/tools/__init__.py
nanugo/tools/images.py
nanugo/tools/utils.py
nanugo/tools/validations.py
nanugo-1.0.3.dist-info/LICENSE
nanugo-1.0.3.dist-info/METADATA
nanugo-1.0.3.dist-info/WHEEL
nanugo-1.0.3.dist-info/entry_points.txt
nanugo-1.0.3.dist-info/RECORD
