Metadata-Version: 2.1
Name: nanugo
Version: 1.0.3
Summary: Turn your handwritten pdf sheets to Anki deck.
License: GPL-3.0-or-later
Author: Lewis Lee
Author-email: shlewislee@gmail.com
Requires-Python: >=3.8,<4.0
Classifier: License :: OSI Approved :: GNU General Public License v3 or later (GPLv3+)
Classifier: Programming Language :: Python :: 3
Classifier: Programming Language :: Python :: 3.8
Classifier: Programming Language :: Python :: 3.9
Classifier: Programming Language :: Python :: 3.10
Classifier: Programming Language :: Python :: 3.11
Classifier: Programming Language :: Python :: 3.12
Requires-Dist: Pillow (>=10.0.0,<11.0.0)
Requires-Dist: genanki (>=0.13.0,<0.14.0)
Requires-Dist: pypdfium2 (>=4.18.0,<5.0.0)
